README.md
setup.py
azweb3/__init__.py
azweb3.egg-info/PKG-INFO
azweb3.egg-info/SOURCES.txt
azweb3.egg-info/dependency_links.txt
azweb3.egg-info/top_level.txt
azweb3/evm/__init__.py
azweb3/evm/account.py
azweb3/evm/contract.py
azweb3/evm/main.py
azweb3/evm/server.py
azweb3/evm/soliditycontract.py
azweb3/evm/wallet.py