Metadata-Version: 2.1
Name: azweb3
Version: 0.0.1
Summary: web3 tools
Author: AndyZhu
Author-email: andyzhu@live.com
